save_scenario_modal/__init__.py
save_scenario_modal/frontend/build/asset-manifest.json
save_scenario_modal/frontend/build/favicon.ico
save_scenario_modal/frontend/build/index.html
save_scenario_modal/frontend/build/logo192.png
save_scenario_modal/frontend/build/logo512.png
save_scenario_modal/frontend/build/manifest.json
save_scenario_modal/frontend/build/robots.txt
save_scenario_modal/frontend/build/static/css/main.e6c13ad2.css
save_scenario_modal/frontend/build/static/css/main.e6c13ad2.css.map
save_scenario_modal/frontend/build/static/js/787.cda612ba.chunk.js
save_scenario_modal/frontend/build/static/js/787.cda612ba.chunk.js.map
save_scenario_modal/frontend/build/static/js/main.af993ea2.js
save_scenario_modal/frontend/build/static/js/main.af993ea2.js.LICENSE.txt
save_scenario_modal/frontend/build/static/js/main.af993ea2.js.map
save_scenario_modal-1.4.0.dist-info/METADATA
save_scenario_modal-1.4.0.dist-info/WHEEL
save_scenario_modal-1.4.0.dist-info/top_level.txt
save_scenario_modal-1.4.0.dist-info/RECORD
