Metadata-Version: 2.1
Name: save-scenario-modal
Version: 1.4.0
Home-page: 
Author: 
Author-email: 
Requires-Python: >=3.6
Requires-Dist: streamlit >=0.66
